INSTALL.rst
LICENSE
MANIFEST.in
README.rst
VERSION
requirements.txt
setup.py
tasks.py
src/ejudge/__init__.py
src/ejudge/__main__.py
src/ejudge/__meta__.py
src/ejudge/build_manager.py
src/ejudge/builtins_ctrl.py
src/ejudge/exceptions.py
src/ejudge/execution_manager.py
src/ejudge/functions.py
src/ejudge/registry_class.py
src/ejudge/util.py
src/ejudge.egg-info/PKG-INFO
src/ejudge.egg-info/SOURCES.txt
src/ejudge.egg-info/dependency_links.txt
src/ejudge.egg-info/entry_points.txt
src/ejudge.egg-info/not-zip-safe
src/ejudge.egg-info/requires.txt
src/ejudge.egg-info/top_level.txt
src/ejudge/langs/__init__.py
src/ejudge/langs/c_family.py
src/ejudge/langs/python_family.py
src/ejudge/langs/pytuga.py
src/ejudge/langs/ruby.py
src/ejudge/tests/__init__.py
src/ejudge/tests/__main__.py
src/ejudge/tests/abstract.py
src/ejudge/tests/test_documentation.py
src/ejudge/tests/test_ejudge.py
src/ejudge/tests/test_examples.py
src/ejudge/tests/test_language_gcc.py
src/ejudge/tests/test_language_python2.py
src/ejudge/tests/test_language_python3.py
src/ejudge/tests/test_language_pytuga.py
src/ejudge/tests/examples/__init__.py
src/ejudge/tests/examples/base.py
src/ejudge/tests/examples/simple.py
src/ejudge/tests/examples/simple_build.py
src/ejudge/tests/examples/simple_extrainput.py
src/ejudge/tests/examples/simple_presentation.py
src/ejudge/tests/examples/simple_template.py
src/ejudge/tests/examples/simple_timeout.py
src/ejudge/tests/examples/simple_unexpected.py
src/ejudge/tests/examples/simple_unusedinput.py
src/ejudge/tests/examples/simple_wrong.py